README.md
setup.py
scripts/stravatool-helper.py
stravatool/__init__.py
stravatool.egg-info/PKG-INFO
stravatool.egg-info/SOURCES.txt
stravatool.egg-info/dependency_links.txt
stravatool.egg-info/requires.txt
stravatool.egg-info/top_level.txt