Metadata-Version: 2.1
Name: stravatool
Version: 0.1.0
Summary: A tool to help with strava's api.
Home-page: https://gitlab.com/rveach/stravatool/
Author: Ryan Veach
Author-email: rveach@gmail.com
License: MIT
Keywords: Strava,API
Platform: UNKNOWN
Classifier: Development Status :: 3 - Alpha
Classifier: Intended Audience :: Developers
Classifier: License :: OSI Approved :: MIT License
Classifier: Operating System :: OS Independent
Classifier: Topic :: Software Development :: Libraries :: Python Modules
Classifier: Topic :: Internet
Classifier: Programming Language :: Python :: 3
Requires-Python: >=3.5
